{
  "AssetMap": {
    "TileSheets\\tools": "Microsoft.Xna.Framework.Graphics.Texture2D",
    "Maps\\springobjects": "Microsoft.Xna.Framework.Graphics.Texture2D",
    "Fonts\\SpriteFont1": "Microsoft.Xna.Framework.Graphics.SpriteFont",
    "Fonts\\SmallFont": "Microsoft.Xna.Framework.Graphics.SpriteFont",
    "Fonts\\tinyFont": "Microsoft.Xna.Framework.Graphics.SpriteFont",
    "Fonts\\tinyFontBorder": "Microsoft.Xna.Framework.Graphics.SpriteFont",
    "Data\\ObjectInformation": "System.Collections.Generic.Dictionary\u00602\u003CSystem.Int32,System.String\u003E",
    "Data\\ClothingInformation": "System.Collections.Generic.Dictionary\u00602\u003CSystem.Int32,System.String\u003E",
    "Data\\BigCraftablesInformation": "System.Collections.Generic.Dictionary\u00602\u003CSystem.Int32,System.String\u003E",
    "Data\\Achievements": "System.Collections.Generic.Dictionary\u00602\u003CSystem.Int32,System.String\u003E",
    "Data\\CraftingRecipes": "System.Collections.Generic.Dictionary\u00602\u003CSystem.String,System.String\u003E",
    "Data\\CookingRecipes": "System.Collections.Generic.Dictionary\u00602\u003CSystem.String,System.String\u003E",
    "LooseSprites\\Cursors": "Microsoft.Xna.Framework.Graphics.Texture2D",
    "LooseSprites\\Cursors2": "Microsoft.Xna.Framework.Graphics.Texture2D",
    "LooseSprites\\Giftbox": "Microsoft.Xna.Framework.Graphics.Texture2D",
    "LooseSprites\\ControllerMaps": "Microsoft.Xna.Framework.Graphics.Texture2D",
    "Data\\NPCGiftTastes": "System.Collections.Generic.Dictionary\u00602\u003CSystem.String,System.String\u003E",
    "Data\\SecretNotes": "System.Collections.Generic.Dictionary\u00602\u003CSystem.Int32,System.String\u003E",
    "LooseSprites\\Concessions": "Microsoft.Xna.Framework.Graphics.Texture2D",
    "LooseSprites\\birds": "Microsoft.Xna.Framework.Graphics.Texture2D",
    "LooseSprites\\daybg": "Microsoft.Xna.Framework.Graphics.Texture2D",
    "LooseSprites\\nightbg": "Microsoft.Xna.Framework.Graphics.Texture2D",
    "Maps\\MenuTiles": "Microsoft.Xna.Framework.Graphics.Texture2D",
    "Maps\\MenuTilesUncolored": "Microsoft.Xna.Framework.Graphics.Texture2D",
    "LooseSprites\\Lighting\\lantern": "Microsoft.Xna.Framework.Graphics.Texture2D",
    "LooseSprites\\Lighting\\windowLight": "Microsoft.Xna.Framework.Graphics.Texture2D",
    "LooseSprites\\Lighting\\sconceLight": "Microsoft.Xna.Framework.Graphics.Texture2D",
    "LooseSprites\\Lighting\\greenLight": "Microsoft.Xna.Framework.Graphics.Texture2D",
    "LooseSprites\\Lighting\\indoorWindowLight": "Microsoft.Xna.Framework.Graphics.Texture2D",
    "LooseSprites\\shadow": "Microsoft.Xna.Framework.Graphics.Texture2D",
    "TileSheets\\animations": "Microsoft.Xna.Framework.Graphics.Texture2D",
    "TileSheets\\crops": "Microsoft.Xna.Framework.Graphics.Texture2D",
    "TileSheets\\emotes": "Microsoft.Xna.Framework.Graphics.Texture2D",
    "TileSheets\\debris": "Microsoft.Xna.Framework.Graphics.Texture2D",
    "TileSheets\\Craftables": "Microsoft.Xna.Framework.Graphics.Texture2D",
    "TileSheets\\rain": "Microsoft.Xna.Framework.Graphics.Texture2D",
    "TileSheets\\BuffsIcons": "Microsoft.Xna.Framework.Graphics.Texture2D",
    "Data\\ObjectContextTags": "System.Collections.Generic.Dictionary\u00602\u003CSystem.String,System.String\u003E",
    "Characters\\Farmer\\hairstyles": "Microsoft.Xna.Framework.Graphics.Texture2D",
    "Characters\\Farmer\\shirts": "Microsoft.Xna.Framework.Graphics.Texture2D",
    "Characters\\Farmer\\pants": "Microsoft.Xna.Framework.Graphics.Texture2D",
    "Characters\\Farmer\\hats": "Microsoft.Xna.Framework.Graphics.Texture2D",
    "Characters\\Farmer\\accessories": "Microsoft.Xna.Framework.Graphics.Texture2D",
    "TileSheets\\furniture": "Microsoft.Xna.Framework.Graphics.Texture2D",
    "TileSheets\\furnitureFront": "Microsoft.Xna.Framework.Graphics.Texture2D",
    "TileSheets\\ChairTiles": "Microsoft.Xna.Framework.Graphics.Texture2D",
    "LooseSprites\\font_bold": "Microsoft.Xna.Framework.Graphics.Texture2D",
    "LooseSprites\\font_colored": "Microsoft.Xna.Framework.Graphics.Texture2D",
    "TileSheets\\weapons": "Microsoft.Xna.Framework.Graphics.Texture2D",
    "TileSheets\\Projectiles": "Microsoft.Xna.Framework.Graphics.Texture2D",
    "Portraits\\George": "Microsoft.Xna.Framework.Graphics.Texture2D",
    "Portraits\\Evelyn": "Microsoft.Xna.Framework.Graphics.Texture2D",
    "Portraits\\Alex": "Microsoft.Xna.Framework.Graphics.Texture2D",
    "Portraits\\Emily": "Microsoft.Xna.Framework.Graphics.Texture2D",
    "Portraits\\Haley": "Microsoft.Xna.Framework.Graphics.Texture2D",
    "Portraits\\Jodi": "Microsoft.Xna.Framework.Graphics.Texture2D",
    "Portraits\\Sam": "Microsoft.Xna.Framework.Graphics.Texture2D",
    "Portraits\\Vincent": "Microsoft.Xna.Framework.Graphics.Texture2D",
    "Portraits\\Clint": "Microsoft.Xna.Framework.Graphics.Texture2D",
    "Portraits\\Lewis": "Microsoft.Xna.Framework.Graphics.Texture2D",
    "Portraits\\Caroline": "Microsoft.Xna.Framework.Graphics.Texture2D",
    "Portraits\\Abigail": "Microsoft.Xna.Framework.Graphics.Texture2D",
    "Portraits\\Pierre": "Microsoft.Xna.Framework.Graphics.Texture2D",
    "Portraits\\Gus": "Microsoft.Xna.Framework.Graphics.Texture2D",
    "Portraits\\Pam": "Microsoft.Xna.Framework.Graphics.Texture2D",
    "Portraits\\Penny": "Microsoft.Xna.Framework.Graphics.Texture2D",
    "Portraits\\Harvey": "Microsoft.Xna.Framework.Graphics.Texture2D",
    "Portraits\\Elliott": "Microsoft.Xna.Framework.Graphics.Texture2D",
    "Portraits\\Maru": "Microsoft.Xna.Framework.Graphics.Texture2D",
    "Portraits\\Robin": "Microsoft.Xna.Framework.Graphics.Texture2D",
    "Portraits\\Demetrius": "Microsoft.Xna.Framework.Graphics.Texture2D",
    "Portraits\\Sebastian": "Microsoft.Xna.Framework.Graphics.Texture2D",
    "Portraits\\Linus": "Microsoft.Xna.Framework.Graphics.Texture2D",
    "Portraits\\Wizard": "Microsoft.Xna.Framework.Graphics.Texture2D",
    "Portraits\\Marnie": "Microsoft.Xna.Framework.Graphics.Texture2D",
    "Portraits\\Shane": "Microsoft.Xna.Framework.Graphics.Texture2D",
    "Portraits\\Jas": "Microsoft.Xna.Framework.Graphics.Texture2D",
    "Portraits\\Leah": "Microsoft.Xna.Framework.Graphics.Texture2D",
    "Portraits\\Dwarf": "Microsoft.Xna.Framework.Graphics.Texture2D",
    "Portraits\\Krobus": "Microsoft.Xna.Framework.Graphics.Texture2D",
    "Portraits\\MrQi": "Microsoft.Xna.Framework.Graphics.Texture2D",
    "Portraits\\Sandy": "Microsoft.Xna.Framework.Graphics.Texture2D",
    "Portraits\\Bouncer": "Microsoft.Xna.Framework.Graphics.Texture2D",
    "Portraits\\Gunther": "Microsoft.Xna.Framework.Graphics.Texture2D",
    "Portraits\\Marlon": "Microsoft.Xna.Framework.Graphics.Texture2D",
    "Portraits\\Henchman": "Microsoft.Xna.Framework.Graphics.Texture2D",
    "Portraits\\Willy": "Microsoft.Xna.Framework.Graphics.Texture2D",
    "Portraits\\ParrotBoy": "Microsoft.Xna.Framework.Graphics.Texture2D",
    "Portraits\\Birdie": "Microsoft.Xna.Framework.Graphics.Texture2D",
    "Portraits\\Kent": "Microsoft.Xna.Framework.Graphics.Texture2D",
    "Data\\NPCDispositions": "System.Collections.Generic.Dictionary\u00602\u003CSystem.String,System.String\u003E",
    "BuildingUpgrades\\Greenhouse": "Microsoft.Xna.Framework.Graphics.Texture2D",
    "Data\\Quests": "System.Collections.Generic.Dictionary\u00602\u003CSystem.Int32,System.String\u003E",
    "Data\\weapons": "System.Collections.Generic.Dictionary\u00602\u003CSystem.Int32,System.String\u003E",
    "Data\\furniture": "System.Collections.Generic.Dictionary\u00602\u003CSystem.Int32,System.String\u003E",
    "Data\\mail": "System.Collections.Generic.Dictionary\u00602\u003CSystem.String,System.String\u003E",
    "Data\\Monsters": "System.Collections.Generic.Dictionary\u00602\u003CSystem.String,System.String\u003E",
    "Maps\\Festivals": "Microsoft.Xna.Framework.Graphics.Texture2D",
    "LooseSprites\\Movies": "Microsoft.Xna.Framework.Graphics.Texture2D",
    "LooseSprites\\temporary_sprites_1": "Microsoft.Xna.Framework.Graphics.Texture2D",
    "TileSheets\\critters": "Microsoft.Xna.Framework.Graphics.Texture2D",
    "TileSheets\\bushes": "Microsoft.Xna.Framework.Graphics.Texture2D",
    "Maps\\MovieTheaterScreen_TileSheet": "Microsoft.Xna.Framework.Graphics.Texture2D",
    "Characters\\Monsters\\Wilderness Golem": "Microsoft.Xna.Framework.Graphics.Texture2D",
    "Data\\HomeRenovations": "System.Collections.Generic.Dictionary\u00602\u003CSystem.String,StardewValley.GameData.HomeRenovations.HomeRenovation\u003E",
    "LooseSprites\\GemBird": "Microsoft.Xna.Framework.Graphics.Texture2D",
    "Data\\SpecialOrders": "System.Collections.Generic.Dictionary\u00602\u003CSystem.String,StardewValley.GameData.SpecialOrderData\u003E",
    "Minigames\\Clouds": "Microsoft.Xna.Framework.Graphics.Texture2D",
    "LooseSprites\\Bat": "Microsoft.Xna.Framework.Graphics.Texture2D",
    "Data\\Blueprints": "System.Collections.Generic.Dictionary\u00602\u003CSystem.String,System.String\u003E",
    "LooseSprites\\robinAtWork": "Microsoft.Xna.Framework.Graphics.Texture2D",
    "Characters\\Farmer\\shoeColors": "Microsoft.Xna.Framework.Graphics.Texture2D",
    "Characters\\Farmer\\skinColors": "Microsoft.Xna.Framework.Graphics.Texture2D",
    "Data\\SpousePatios": "System.Collections.Generic.Dictionary\u00602\u003CSystem.String,System.String\u003E",
    "Buildings\\houses": "Microsoft.Xna.Framework.Graphics.Texture2D",
    "Data\\FarmAnimals": "System.Collections.Generic.Dictionary\u00602\u003CSystem.String,System.String\u003E",
    "Data\\Fish": "System.Collections.Generic.Dictionary\u00602\u003CSystem.Int32,System.String\u003E",
    "LooseSprites\\Lighting\\projectorLight": "Microsoft.Xna.Framework.Graphics.Texture2D",
    "LooseSprites\\Lighting\\fishTankLight": "Microsoft.Xna.Framework.Graphics.Texture2D",
    "LooseSprites\\SeaMonster": "Microsoft.Xna.Framework.Graphics.Texture2D",
    "Data\\Crops": "System.Collections.Generic.Dictionary\u00602\u003CSystem.Int32,System.String\u003E",
    "Data\\HairData": "System.Collections.Generic.Dictionary\u00602\u003CSystem.Int32,System.String\u003E",
    "Data\\ChairTiles": "System.Collections.Generic.Dictionary\u00602\u003CSystem.String,System.String\u003E",
    "Portraits\\AnsweringMachine": "Microsoft.Xna.Framework.Graphics.Texture2D",
    "Data\\Locations": "System.Collections.Generic.Dictionary\u00602\u003CSystem.String,System.String\u003E",
    "Data\\Events\\FarmHouse": "System.Collections.Generic.Dictionary\u00602\u003CSystem.String,System.String\u003E",
    "Data\\Events\\Trailer": "System.Collections.Generic.Dictionary\u00602\u003CSystem.String,System.String\u003E",
    "Data\\EngagementDialogue": "System.Collections.Generic.Dictionary\u00602\u003CSystem.String,System.String\u003E",
    "Characters\\Dialogue\\MarriageDialogue": "System.Collections.Generic.Dictionary\u00602\u003CSystem.String,System.String\u003E",
    "Characters\\Dialogue\\rainy": "System.Collections.Generic.Dictionary\u00602\u003CSystem.String,System.String\u003E",
    "Data\\animationDescriptions": "System.Collections.Generic.Dictionary\u00602\u003CSystem.String,System.String\u003E",
    "Data\\AdditionalFarms": "System.Collections.Generic.List\u00601\u003CStardewValley.GameData.ModFarmType\u003E",
    "Data\\AdditionalLanguages": "System.Collections.Generic.List\u00601\u003CStardewValley.GameData.ModLanguage\u003E",
    "Data\\Festivals\\FestivalDates": "System.Collections.Generic.Dictionary\u00602\u003CSystem.String,System.String\u003E",
    "Data\\Furniture": "System.Collections.Generic.Dictionary\u00602\u003CSystem.Int32,System.String\u003E",
    "Data\\Boots": "System.Collections.Generic.Dictionary\u00602\u003CSystem.Int32,System.String\u003E",
    "Data\\hats": "System.Collections.Generic.Dictionary\u00602\u003CSystem.Int32,System.String\u003E",
    "Data//CookingRecipes": "System.Collections.Generic.Dictionary\u00602\u003CSystem.String,System.String\u003E",
    "Data\\achievements": "System.Collections.Generic.Dictionary\u00602\u003CSystem.Int32,System.String\u003E",
    "Data\\AdditionalWallpaperFlooring": "System.Collections.Generic.List\u00601\u003CStardewValley.GameData.ModWallpaperOrFlooring\u003E",
    "TerrainFeatures\\Flooring": "Microsoft.Xna.Framework.Graphics.Texture2D",
    "TerrainFeatures\\Flooring_winter": "Microsoft.Xna.Framework.Graphics.Texture2D",
    "Data\\fruitTrees": "System.Collections.Generic.Dictionary\u00602\u003CSystem.Int32,System.String\u003E",
    "TileSheets\\fruitTrees": "Microsoft.Xna.Framework.Graphics.Texture2D",
    "TerrainFeatures\\hoeDirt": "Microsoft.Xna.Framework.Graphics.Texture2D",
    "TerrainFeatures\\hoeDirtDark": "Microsoft.Xna.Framework.Graphics.Texture2D",
    "TerrainFeatures\\hoeDirtSnow": "Microsoft.Xna.Framework.Graphics.Texture2D",
    "TerrainFeatures\\Quartz": "Microsoft.Xna.Framework.Graphics.Texture2D",
    "TerrainFeatures\\mushroom_tree": "Microsoft.Xna.Framework.Graphics.Texture2D",
    "TerrainFeatures\\tree_palm2": "Microsoft.Xna.Framework.Graphics.Texture2D",
    "TerrainFeatures\\tree_palm": "Microsoft.Xna.Framework.Graphics.Texture2D",
    "LooseSprites\\AquariumFish": "Microsoft.Xna.Framework.Graphics.Texture2D",
    "Data\\AquariumFish": "System.Collections.Generic.Dictionary\u00602\u003CSystem.Int32,System.String\u003E",
    "Portraits\\Bear": "Microsoft.Xna.Framework.Graphics.Texture2D",
    "Data\\TV\\TipChannel": "System.Collections.Generic.Dictionary\u00602\u003CSystem.String,System.String\u003E",
    "Data\\TV\\CookingChannel": "System.Collections.Generic.Dictionary\u00602\u003CSystem.String,System.String\u003E",
    "Maps\\walls_and_floors": "Microsoft.Xna.Framework.Graphics.Texture2D",
    "Data\\Bundles": "System.Collections.Generic.Dictionary\u00602\u003CSystem.String,System.String\u003E",
    "Minigames\\Darts": "Microsoft.Xna.Framework.Graphics.Texture2D",
    "Minigames\\boatJourneyMap": "Microsoft.Xna.Framework.Graphics.Texture2D",
    "Effects\\ShadowRemoveMG3.8.0": "Microsoft.Xna.Framework.Graphics.Effect",
    "LooseSprites\\CraneGame": "Microsoft.Xna.Framework.Graphics.Texture2D",
    "Minigames\\MineCart": "Microsoft.Xna.Framework.Graphics.Texture2D",
    "Minigames\\MaruComet": "Microsoft.Xna.Framework.Graphics.Texture2D",
    "Minigames\\jojacorps": "Microsoft.Xna.Framework.Graphics.Texture2D",
    "LooseSprites\\boardGame": "Microsoft.Xna.Framework.Graphics.Texture2D",
    "LooseSprites\\boardGameBorder": "Microsoft.Xna.Framework.Graphics.Texture2D",
    "LooseSprites\\cowPhotos": "Microsoft.Xna.Framework.Graphics.Texture2D",
    "LooseSprites\\cowPhotosWinter": "Microsoft.Xna.Framework.Graphics.Texture2D",
    "Minigames\\Intro": "Microsoft.Xna.Framework.Graphics.Texture2D",
    "Maps\\spring_outdoorsTileSheet": "Microsoft.Xna.Framework.Graphics.Texture2D",
    "LooseSprites\\nightSceneMaru": "Microsoft.Xna.Framework.Graphics.Texture2D",
    "LooseSprites\\nightSceneMaruTrees": "Microsoft.Xna.Framework.Graphics.Texture2D",
    "LooseSprites\\SpecialOrdersBoard": "Microsoft.Xna.Framework.Graphics.Texture2D",
    "Data\\PaintData": "System.Collections.Generic.Dictionary\u00602\u003CSystem.String,System.String\u003E",
    "LooseSprites\\dye_bench": "Microsoft.Xna.Framework.Graphics.Texture2D",
    "LooseSprites\\FieldOfficeDonationMenu": "Microsoft.Xna.Framework.Graphics.Texture2D",
    "LooseSprites\\ForgeMenu": "Microsoft.Xna.Framework.Graphics.Texture2D",
    "LooseSprites\\EmoteMenu": "Microsoft.Xna.Framework.Graphics.Texture2D",
    "LooseSprites\\letterBG": "Microsoft.Xna.Framework.Graphics.Texture2D",
    "LooseSprites\\tailoring": "Microsoft.Xna.Framework.Graphics.Texture2D",
    "Data\\TailoringRecipes": "System.Collections.Generic.List\u00601\u003CStardewValley.GameData.Crafting.TailorItemRecipe\u003E",
    "Strings\\credits": "System.Collections.Generic.List\u00601\u003CSystem.String\u003E",
    "LooseSprites\\Billboard": "Microsoft.Xna.Framework.Graphics.Texture2D",
    "LooseSprites\\buildingPlacementTiles": "Microsoft.Xna.Framework.Graphics.Texture2D",
    "LooseSprites\\textBox": "Microsoft.Xna.Framework.Graphics.Texture2D",
    "LooseSprites\\chatBox": "Microsoft.Xna.Framework.Graphics.Texture2D",
    "LooseSprites\\emojis": "Microsoft.Xna.Framework.Graphics.Texture2D",
    "TileSheets\\SecretNotesImages": "Microsoft.Xna.Framework.Graphics.Texture2D",
    "LooseSprites\\farmMap": "Microsoft.Xna.Framework.Graphics.Texture2D",
    "LooseSprites//temporary_sprites_1": "Microsoft.Xna.Framework.Graphics.Texture2D",
    "LooseSprites\\JunimoNote": "Microsoft.Xna.Framework.Graphics.Texture2D",
    "LooseSprites\\LanguageButtons": "Microsoft.Xna.Framework.Graphics.Texture2D",
    "LooseSprites\\map": "Microsoft.Xna.Framework.Graphics.Texture2D",
    "Minigames\\TitleButtons": "Microsoft.Xna.Framework.Graphics.Texture2D",
    "LooseSprites\\TutorialImages\\FarmTut": "Microsoft.Xna.Framework.Graphics.Texture2D",
    "Data\\Events\\AbandonedJojaMart": "System.Collections.Generic.Dictionary\u00602\u003CSystem.String,System.String\u003E",
    "LooseSprites\\WillysBoat": "Microsoft.Xna.Framework.Graphics.Texture2D",
    "LooseSprites\\parrots": "Microsoft.Xna.Framework.Graphics.Texture2D",
    "Portraits\\SafariGuy": "Microsoft.Xna.Framework.Graphics.Texture2D",
    "LooseSprites\\LightRays": "Microsoft.Xna.Framework.Graphics.Texture2D",
    "LooseSprites\\Cloudy_Ocean_BG": "Microsoft.Xna.Framework.Graphics.Texture2D",
    "LooseSprites\\Cloudy_Ocean_BG_Night": "Microsoft.Xna.Framework.Graphics.Texture2D",
    "VolcanoLayouts\\Layouts": "Microsoft.Xna.Framework.Graphics.Texture2D",
    "Data\\MoviesReactions": "System.Collections.Generic.List\u00601\u003CStardewValley.GameData.Movies.MovieCharacterReaction\u003E",
    "Data\\ConcessionTastes": "System.Collections.Generic.List\u00601\u003CStardewValley.GameData.Movies.ConcessionTaste\u003E",
    "Data\\Movies": "System.Collections.Generic.Dictionary\u00602\u003CSystem.String,StardewValley.GameData.Movies.MovieData\u003E",
    "Data\\Concessions": "System.Collections.Generic.List\u00601\u003CStardewValley.GameData.Movies.ConcessionItemData\u003E",
    "Portraits\\Gil": "Microsoft.Xna.Framework.Graphics.Texture2D",
    "Portraits\\Dobson": "Microsoft.Xna.Framework.Graphics.Texture2D",
    "LooseSprites\\steamAnimation": "Microsoft.Xna.Framework.Graphics.Texture2D",
    "LooseSprites\\swimShadow": "Microsoft.Xna.Framework.Graphics.Texture2D",
    "Maps\\CommunityCenter_Refurbished": "xTile.Map",
    "Data\\SpouseRooms": "System.Collections.Generic.Dictionary\u00602\u003CSystem.String,System.String\u003E",
    "LooseSprites\\JojaCDForm": "Microsoft.Xna.Framework.Graphics.Texture2D",
    "Portraits\\Morris": "Microsoft.Xna.Framework.Graphics.Texture2D",
    "Maps\\Mountain-BridgeFixed": "xTile.Map",
    "Characters\\Monsters\\Shadow Brute": "Microsoft.Xna.Framework.Graphics.Texture2D",
    "Characters\\Monsters\\Shadow Shaman": "Microsoft.Xna.Framework.Graphics.Texture2D",
    "Characters\\Monsters\\Shadow Sniper": "Microsoft.Xna.Framework.Graphics.Texture2D",
    "Characters\\Monsters\\Frost Bat": "Microsoft.Xna.Framework.Graphics.Texture2D",
    "Characters\\Monsters\\Lava Bat": "Microsoft.Xna.Framework.Graphics.Texture2D",
    "Characters\\Monsters\\Iridium Bat": "Microsoft.Xna.Framework.Graphics.Texture2D",
    "Characters\\Monsters\\Green Slime": "Microsoft.Xna.Framework.Graphics.Texture2D",
    "Data\\FishPondData": "System.Collections.Generic.List\u00601\u003CStardewValley.GameData.FishPond.FishPondData\u003E",
    "LooseSprites\\ParrotPlatform": "Microsoft.Xna.Framework.Graphics.Texture2D",
    "LooseSprites\\SandDuggy": "Microsoft.Xna.Framework.Graphics.Texture2D",
    "LooseSprites\\SuspensionBridge": "Microsoft.Xna.Framework.Graphics.Texture2D"
  },
  "FormerAssets": []
}